<screen name="FootOnsatNotifScreen" position="350,40" zPosition="10" size="650,120" title="Notif" backgroundColor="#101c1c1c" flags="wfNoBorder">
    <widget name="live" zPosition="6" position="655,6" size="100,40" pixmap="/usr/lib/enigma2/python/Plugins/Extensions/FootOnSat/assets/icon/HD/live_icon.png" alphatest="blend" />
    <widget name="compet" zPosition="3" position="7,11" size="190,100" />
    <widget name="flag1" zPosition="5" position="202,45" size="40,30" alphatest="blend" />
    <widget name="flag2" zPosition="5" position="605,45" size="40,30" alphatest="blend" />
    <widget name="match" font="Regular;18" position="195,12" zPosition="2" valign="center" halign="center" size="460,90" backgroundColor="#31000000" transparent="1" />
    <widget name="message" font="Regular;18" position="220,60" zPosition="2" valign="center" halign="center" size="420,71" backgroundColor="#31000000" transparent="1" />
    <ePixmap position="0,0" zPosition="1" size="650,120" pixmap="/usr/lib/enigma2/python/Plugins/Extensions/FootOnSat/assets/icon/HD/notif_bar.png" alphatest="blend" />
    <widget name="live" zPosition="5" position="560,1" size="90,40" pixmap="/usr/lib/enigma2/python/Plugins/Extensions/FootOnSat/assets/icon/HD/live_notif.png" alphatest="blend" />
</screen>